cmd_habit_tracker/__init__.py
cmd_habit_tracker/cli.py
cmd_habit_tracker/main.py
cmd_habit_tracker/ai/__init__.py
cmd_habit_tracker/ai/api.py
cmd_habit_tracker/clogging/__init__.py
cmd_habit_tracker/clogging/config.py
cmd_habit_tracker/db/__init__.py
cmd_habit_tracker/db/models.py
cmd_habit_tracker/db/operations.py
cmd_habit_tracker/db/queries.py
cmd_habit_tracker/exceptions/__init__.py
cmd_habit_tracker/exceptions/errors.py
cmd_habit_tracker/utils/__init__.py
cmd_habit_tracker/utils/aux.py
cmd_habit_tracker/utils/data.py
cmd_habit_tracker-1.0.5.dist-info/METADATA
cmd_habit_tracker-1.0.5.dist-info/WHEEL
cmd_habit_tracker-1.0.5.dist-info/entry_points.txt
cmd_habit_tracker-1.0.5.dist-info/licenses/LICENSE.MIT
cmd_habit_tracker-1.0.5.dist-info/RECORD
