Metadata-Version: 2.4
Name: cmd_habit_tracker
Version: 1.0.5
Summary: Command-line habit tracker with AI suggestions, customizable tracking, and user-friendly interface.
Project-URL: Homepage, https://github.com/abdallacodes/cmd-habit-tracker.git
Author-email: Abdalla Egbareia <habitcmd@gmail.com>
License: MIT License
License-File: LICENSE.MIT
Keywords: ai-suggestions,cli,command-line,customizable,goal-tracking,habit-building,habit-tracker,personal-development,productivity,python,self-improvement,time-management,tracking-tool,user-friendly
Classifier: Operating System :: OS Independent
Classifier: Programming Language :: Python :: 3
Requires-Python: >=3.8
Requires-Dist: pandas
Requires-Dist: platformdirs
Requires-Dist: requests
Requires-Dist: tabulate
